Workbook

Sheet Inventario
A1: INVENTARIO DE HERRAMIENTAS DIGITALES (datos ficticios de ejemplo: reemplázalos por los de tu institución)
A2: Puntúa 0 = no, 1 = parcial, 2 = sí. Integración: comparte datos con los sistemas centrales. Utilidad: hay evidencia local de uso pedagógico. Sostenibilidad: tiene responsable, presupuesto y plan de salida de datos.
A4: Herramienta | B4: Función | C4: Usuarios activos | D4: Costo anual (COP) | E4: Maneja datos personales | F4: Integración (0-2) | G4: Utilidad pedagógica (0-2) | H4: Sostenibilidad (0-2) | I4: Puntaje | J4: Función duplicada | K4: Decisión sugerida
A5: Plataforma académica (notas y boletines) | B5: Gestión académica | C5: 1200 | D5: 18000000 | E5: Sí | F5: 2 | G5: 2 | H5: 2 | I5: =SUM(F5:H5) | J5: =IF(COUNTIF($B$5:$B$16,B5)>1,"Sí","No") | K5: =IF(OR(G5=0,I5<=2),"Retirar o reemplazar",IF(AND(J5="Sí",I5<_xlfn.MAXIFS($I$5:$I$16,$B$5:$B$16,B5)),"Fusionar en la mejor",IF(I5>=5,"Mantener","Revisar")))
A6: Aula virtual A (institucional) | B6: Aula virtual | C6: 400 | D6: 6000000 | E6: Sí | F6: 1 | G6: 2 | H6: 1 | I6: =SUM(F6:H6) | J6: =IF(COUNTIF($B$5:$B$16,B6)>1,"Sí","No") | K6: =IF(OR(G6=0,I6<=2),"Retirar o reemplazar",IF(AND(J6="Sí",I6<_xlfn.MAXIFS($I$5:$I$16,$B$5:$B$16,B6)),"Fusionar en la mejor",IF(I6>=5,"Mantener","Revisar")))
A7: Aula virtual B (cuenta de un docente) | B7: Aula virtual | C7: 90 | D7: 0 | E7: Sí | F7: 0 | G7: 1 | H7: 0 | I7: =SUM(F7:H7) | J7: =IF(COUNTIF($B$5:$B$16,B7)>1,"Sí","No") | K7: =IF(OR(G7=0,I7<=2),"Retirar o reemplazar",IF(AND(J7="Sí",I7<_xlfn.MAXIFS($I$5:$I$16,$B$5:$B$16,B7)),"Fusionar en la mejor",IF(I7>=5,"Mantener","Revisar")))
A8: App de mensajería a familias | B8: Comunicación con familias | C8: 900 | D8: 4800000 | E8: Sí | F8: 1 | G8: 2 | H8: 1 | I8: =SUM(F8:H8) | J8: =IF(COUNTIF($B$5:$B$16,B8)>1,"Sí","No") | K8: =IF(OR(G8=0,I8<=2),"Retirar o reemplazar",IF(AND(J8="Sí",I8<_xlfn.MAXIFS($I$5:$I$16,$B$5:$B$16,B8)),"Fusionar en la mejor",IF(I8>=5,"Mantener","Revisar")))
A9: Grupos de WhatsApp por curso | B9: Comunicación con familias | C9: 900 | D9: 0 | E9: Sí | F9: 0 | G9: 1 | H9: 0 | I9: =SUM(F9:H9) | J9: =IF(COUNTIF($B$5:$B$16,B9)>1,"Sí","No") | K9: =IF(OR(G9=0,I9<=2),"Retirar o reemplazar",IF(AND(J9="Sí",I9<_xlfn.MAXIFS($I$5:$I$16,$B$5:$B$16,B9)),"Fusionar en la mejor",IF(I9>=5,"Mantener","Revisar")))
A10: Plataforma de práctica de matemáticas A | B10: Práctica de matemáticas | C10: 250 | D10: 7500000 | E10: Sí | F10: 0 | G10: 2 | H10: 1 | I10: =SUM(F10:H10) | J10: =IF(COUNTIF($B$5:$B$16,B10)>1,"Sí","No") | K10: =IF(OR(G10=0,I10<=2),"Retirar o reemplazar",IF(AND(J10="Sí",I10<_xlfn.MAXIFS($I$5:$I$16,$B$5:$B$16,B10)),"Fusionar en la mejor",IF(I10>=5,"Mantener","Revisar")))
A11: Plataforma de práctica de matemáticas B | B11: Práctica de matemáticas | C11: 60 | D11: 3000000 | E11: Sí | F11: 0 | G11: 1 | H11: 0 | I11: =SUM(F11:H11) | J11: =IF(COUNTIF($B$5:$B$16,B11)>1,"Sí","No") | K11: =IF(OR(G11=0,I11<=2),"Retirar o reemplazar",IF(AND(J11="Sí",I11<_xlfn.MAXIFS($I$5:$I$16,$B$5:$B$16,B11)),"Fusionar en la mejor",IF(I11>=5,"Mantener","Revisar")))
A12: Generador de presentaciones con IA | B12: Creación de contenidos | C12: 30 | D12: 2400000 | E12: No | F12: 0 | G12: 1 | H12: 0 | I12: =SUM(F12:H12) | J12: =IF(COUNTIF($B$5:$B$16,B12)>1,"Sí","No") | K12: =IF(OR(G12=0,I12<=2),"Retirar o reemplazar",IF(AND(J12="Sí",I12<_xlfn.MAXIFS($I$5:$I$16,$B$5:$B$16,B12)),"Fusionar en la mejor",IF(I12>=5,"Mantener","Revisar")))
A13: Suite ofimática | B13: Ofimática | C13: 1300 | D13: 9000000 | E13: Sí | F13: 2 | G13: 2 | H13: 2 | I13: =SUM(F13:H13) | J13: =IF(COUNTIF($B$5:$B$16,B13)>1,"Sí","No") | K13: =IF(OR(G13=0,I13<=2),"Retirar o reemplazar",IF(AND(J13="Sí",I13<_xlfn.MAXIFS($I$5:$I$16,$B$5:$B$16,B13)),"Fusionar en la mejor",IF(I13>=5,"Mantener","Revisar")))
A14: Formularios para evaluaciones | B14: Evaluación en línea | C14: 300 | D14: 0 | E14: Sí | F14: 1 | G14: 2 | H14: 2 | I14: =SUM(F14:H14) | J14: =IF(COUNTIF($B$5:$B$16,B14)>1,"Sí","No") | K14: =IF(OR(G14=0,I14<=2),"Retirar o reemplazar",IF(AND(J14="Sí",I14<_xlfn.MAXIFS($I$5:$I$16,$B$5:$B$16,B14)),"Fusionar en la mejor",IF(I14>=5,"Mantener","Revisar")))
A15: Plataforma de lectura | B15: Lectura | C15: 120 | D15: 5400000 | E15: Sí | F15: 0 | G15: 0 | H15: 1 | I15: =SUM(F15:H15) | J15: =IF(COUNTIF($B$5:$B$16,B15)>1,"Sí","No") | K15: =IF(OR(G15=0,I15<=2),"Retirar o reemplazar",IF(AND(J15="Sí",I15<_xlfn.MAXIFS($I$5:$I$16,$B$5:$B$16,B15)),"Fusionar en la mejor",IF(I15>=5,"Mantener","Revisar")))
A16: Videoconferencia | B16: Videoconferencia | C16: 200 | D16: 3600000 | E16: No | F16: 1 | G16: 1 | H16: 1 | I16: =SUM(F16:H16) | J16: =IF(COUNTIF($B$5:$B$16,B16)>1,"Sí","No") | K16: =IF(OR(G16=0,I16<=2),"Retirar o reemplazar",IF(AND(J16="Sí",I16<_xlfn.MAXIFS($I$5:$I$16,$B$5:$B$16,B16)),"Fusionar en la mejor",IF(I16>=5,"Mantener","Revisar")))

Sheet Resumen
A1: RESUMEN
A3: Herramientas inventariadas | B3: =COUNTA(Inventario!A5:A16)
A4: Costo anual total (COP) | B4: =SUM(Inventario!D5:D16)
A5: Herramientas a retirar o reemplazar | B5: =COUNTIF(Inventario!K5:K16,"Retirar o reemplazar")
A6: Herramientas a fusionar | B6: =COUNTIF(Inventario!K5:K16,"Fusionar en la mejor")
A7: Costo anual de las que se retiran o fusionan (COP) | B7: =SUMIF(Inventario!K5:K16,"Retirar o reemplazar",Inventario!D5:D16)+SUMIF(Inventario!K5:K16,"Fusionar en la mejor",Inventario!D5:D16)
A8: % del costo anual | B8: =B7/B4
A9: Herramientas con datos personales y puntaje de sostenibilidad menor que 2 | B9: =COUNTIFS(Inventario!E5:E16,"Sí",Inventario!H5:H16,"<2")
A11: Nota: la decisión es una sugerencia para abrir la conversación, no una orden. Antes de retirar algo, consulta a quienes lo usan y respalda sus datos. MAXIFS requiere Excel 2019 o Microsoft 365.
